mpesa/__init__.py
mpesa/config.py
mpesa/auth/__init__.py
mpesa/auth/auth.py
mpesa/auth/models.py
mpesa/payments/__init__.py
mpesa/payments/b2c.py
mpesa/payments/c2b.py
mpesa/payments/stk_push.py
mpesa/payments/models/__init__.py
mpesa/payments/models/b2c_model.py
mpesa/payments/models/c2b_model.py
mpesa/payments/models/stk_push_model.py
mpesa/utils/__init__.py
mpesa/utils/client.py
mpesa/utils/error_handler.py
mpesa/utils/exceptions.py
mpesa/utils/logger.py
tests/__init__.py
tests/test_auth.py
tests/test_b2c.py
tests/test_b2c_model.py
tests/test_b2c_request_model.py
tests/test_c2b.py
tests/test_c2b_make_payment.py
tests/test_logger.py
tests/test_register_url_request.py
tests/test_stk_push.py
tests/test_version.py
mpesa_client-1.0.0.dist-info/LICENSE
mpesa_client-1.0.0.dist-info/METADATA
mpesa_client-1.0.0.dist-info/WHEEL
mpesa_client-1.0.0.dist-info/top_level.txt
mpesa_client-1.0.0.dist-info/RECORD
