Metadata-Version: 2.1
Name: mpesa_client
Version: 1.0.0
Summary: A Python SDK for seamless integration with the M-Pesa API, supporting STK Push payments, C2B, B2C payouts, and more.
Home-page: https://github.com/amlaksil/mpesa-sdk
Author: Silamlak Desye
Author-email: Silamlak Desye <lamlak.lamlak19@gmail.com>
License: MIT License        
Project-URL: Homepage, https://github.com/amlaksil/mpesa-sdk
Project-URL: Repository, https://github.com/amlaksil/mpesa-sdk
Classifier: Programming Language :: Python :: 3
Classifier: License :: OSI Approved :: MIT License
Classifier: Operating System :: OS Independent
Requires-Python: >=3.7
License-File: LICENSE
Requires-Dist: pydantic (<3.0.0,>=2.10.0)
Requires-Dist: requests (<3.0.0,>=2.31.0)
Requires-Dist: python-dotenv (<2.0.0,>=1.0.1)
Requires-Dist: requests-oauthlib (<3.0.0,>=2.0.0)
Requires-Dist: requests-toolbelt (<2.0.0,>=1.0.0)
Provides-Extra: dev
Requires-Dist: build ; extra == 'dev'
Requires-Dist: pycodestyle (==2.11.1) ; extra == 'dev'
Requires-Dist: requests-unixsocket (==0.2.0) ; extra == 'dev'
Requires-Dist: typing-extensions (==4.12.2) ; extra == 'dev'
